sport_evo_summary/__init__.py
sport_evo_summary/main.py
sport_evo_summary/prompts.py
sport_evo_summary-2025.12.21182358.dist-info/METADATA
sport_evo_summary-2025.12.21182358.dist-info/WHEEL
sport_evo_summary-2025.12.21182358.dist-info/top_level.txt
sport_evo_summary-2025.12.21182358.dist-info/RECORD
