Metadata-Version: 2.4
Name: sport-evo-summary
Version: 2025.12.21182358
Summary: A new package that transforms unstructured text about sports evolution into a structured summary. Users input text describing changes in a sport, and the package returns a standardized breakdown of ke
Author-email: sport-evo-summary <hi@eugene.plus>
License: MIT
Project-URL: Homepage, https://github.com/chigwell/sport-evo-summary
Requires-Python: >=3.9
Requires-Dist: langchain-llm7>=0.0.0
Requires-Dist: llmatch-messages>=0.0.0
Requires-Dist: langchain-core>=0.3.0
